ddd/__init__.py
ddd/bootstrapper.py
ddd/error.py
ddd/factories.py
ddd/handlers.py
ddd/message_bus.py
ddd/model.py
ddd/repository.py
ddd/unit_of_work.py
py_ddd_framework-0.1.0.dist-info/LICENSE
py_ddd_framework-0.1.0.dist-info/METADATA
py_ddd_framework-0.1.0.dist-info/WHEEL
py_ddd_framework-0.1.0.dist-info/top_level.txt
py_ddd_framework-0.1.0.dist-info/RECORD
