Metadata-Version: 2.1
Name: py-ddd-framework
Version: 0.1.0
Summary: Python Domain-Driven Design (DDD) Framework
Home-page: https://github.com/vklap/py_ddd_framework
Author: Victor Klapholz
Author-email: victor.klapholz@gmail.com
License: MIT
Keywords: DDD Domain Driven Design Framework Domain-Driven
Classifier: Programming Language :: Python :: 3.7
Classifier: Programming Language :: Python :: 3.8
Classifier: Programming Language :: Python :: 3.9
Classifier: Programming Language :: Python :: 3.10
Classifier: Programming Language :: Python :: 3.11
Classifier: License :: OSI Approved :: MIT License
Classifier: Operating System :: OS Independent
License-File: LICENSE
